Workbook

Sheet 1903 Aviation
B11: Last updated: | C11: 46023
B13: Airplane model: | C13: Global 6000
B15: Currency
B16: Currency: | C16: EUR
B17: Dollar / SEK | C17: 9.5
B18: Euro / SEK | C18: 10.9
B19: USD / EUR | C19: 0.85
B20: =+"Fuel Price"&" "&"-"&" "&+'1903 Aviation'!$C$16 -> Fuel Price - EUR | C20: 1.25

Sheet Cost per owner
B2: Cost per owner
B4: =+'1903 Aviation'!C16 -> EUR | C4: Yearly | D4: Monthly | F4: Flight time | G4: Hours
B5: Fixed cost | C5: =+'Fixed costs'!H26 -> 2277076 | D5: =+'Fixed costs'!I26 -> 189756.33 | F5: Flight time owner 1 | G5: 200
B6: =+B4 -> EUR | C6: Hourly | F6: Flight time owner 2 | G6: 100
B7: Variable cost | C7: =+'Variable costs'!I9 -> 4027.5 | F7: Flight time charter | G7: 200
F8: Total Hours | G8: =+SUM(G5:G7) -> 500
B9: Charter
B10: =+"Charter price"&" "&+'1903 Aviation'!$C$16 -> Charter price EUR | C10: 7500
B11: =+"Charter cost"&" "&+'1903 Aviation'!$C$16 -> Charter cost EUR | C11: =+C7 -> 4027.5
B12: Hours charter | C12: =+G7 -> 200
B13: Charter revenue | C13: =+(C10-C11)*C12 -> 694500
B15: New yearly cost | C15: =C5-C13 -> 1582576
B16: New monthly cost | C16: =C15/12 -> 131881.33
B18: =+"Yearly budget"&" "&+'1903 Aviation'!$C$16 -> Yearly budget EUR | C18: Fix Yearly | D18: Fix Montly | E18: Hourly cost
B19: Owner 1 | C19: =(C15/('Cost per owner'!G5+'Cost per owner'!G6))*'Cost per owner'!G5 -> 1055050.7 | D19: =C19/12 -> 87920.889 | E19: =(C19/'Cost per owner'!G5)+C7 -> 9302.7534
B20: Owner 2 | C20: =(C15/(G5+G6))*'Cost per owner'!G6 -> 527525.34 | D20: =C20/12 -> 43960.445 | E20: =(C20/'Cost per owner'!G6)+C7 -> 9302.7534
B21: Note: Average handling + landing fees 3000 - 6000 euro

Sheet Fixed costs
B2: Fixed costs
B4: Nr of captain | C4: 2 | E4: Fixed costs | F4: Input Yearly - EUR | G4: Input Yearly - Dollar | H4: =+"Year"&" "&+'1903 Aviation'!$C$16 -> Year EUR | I4: =+"Month"&" "&+'1903 Aviation'!$C$16 -> Month EUR | K4: Comments:
B5: Cost per pilot (yearly) | C5: =1536000/'1903 Aviation'!C18*C4 -> 281834.86 | E5: Crew | H5: =+C8 -> 493211.01 | I5: =SUM(H5)/12 -> 41100.917 | K5: 2 kaptener och 2 styrmän
B6: Nr of first officer | C6: 2 | E6: Cabin crew | H6: =+C12 -> 76800 | I6: =H6/12 -> 6400 | K6: 1 värdinnor
B7: Cost per first officier (yearly) | C7: =1152000/'1903 Aviation'!C18*C6 -> 211376.15 | E7: Flight engineer | H7: =+C16 -> 76800 | I7: =SUM(H7)/12 -> 6400 | K7: Halv tekniker
B8: =+"Total cost crew (yearly)"&" "&+'1903 Aviation'!$C$16 -> Total cost crew (yearly) EUR | C8: =+C7+C5 -> 493211.01 | E8: Health and travel insurance | F8: 9000 | H8: =IF(F8<>"", F8, IF(G8<>"", G8*$C$18, "")) -> 9000 | I8: =SUM(H8)/12 -> 750 | K8: Personalförsäkringar, reseförsäkring och sjukförsäkring
E9: Management Fee , CAMO | F9: 180000 | H9: =IF(F9<>"", F9, IF(G9<>"", G9*$C$18, "")) -> 180000 | I9: =SUM(H9)/12 -> 15000 | K9: Kostnaden för att ha flygplanet på tillstånd
B10: Nr of cabin crew | C10: 1 | E10: Insurance | F10: 55000 | H10: =IF(F10<>"", F10, IF(G10<>"", G10*$C$18, "")) -> 55000 | I10: =H10/12 -> 4583.3333 | K10: Värde ca 25 musd
B11: Cost per cabin crew (yearly) | C11: 76800 | E11: Motorprogram RR | F11: 343000 | H11: =IF(F11<>"", F11, IF(G11<>"", G11*$C$18, "")) -> 343000 | I11: =H11/12 -> 28583.333 | K11: Motorprogram min 530 000 usd/år 400 h
B12: =+"Total cost cabin crew (yearly)"&" "&+'1903 Aviation'!$C$16 -> Total cost cabin crew (yearly) EUR | C12: =+C11*C10 -> 76800 | E12: Parts, Smartparts + | G12: =330000+(1320*200) -> 594000 | H12: =IF(F12<>"", F12, IF(G12<>"", G12*$C$18, "")) -> 504900 | I12: =SUM(H12)/12 -> 42075 | K12: Reservdelsprogram min 330 000 usd/år 250 h
E13: CAMP | G13: 20000 | H13: =IF(F13<>"", F13, IF(G13<>"", G13*$C$18, "")) -> 17000 | I13: =SUM(H13)/12 -> 1416.6667 | K13: Uppföljningsprogram för flygplanet
B14: Nr of flight engineers | C14: 0.5 | E14: INDS (Nav DB + charts) | G14: 13700 | H14: =IF(F14<>"", F14, IF(G14<>"", G14*$C$18, "")) -> 11645 | I14: =SUM(H14)/12 -> 970.41667 | K14: Navigationskort i cockpit
B15: Cost per flight engineer (yearly) | C15: 153600 | E15: Satcom | G15: 20800 | H15: =IF(F15<>"", F15, IF(G15<>"", G15*$C$18, "")) -> 17680 | I15: =SUM(H15)/12 -> 1473.3333 | K15: Satcom Direct
B16: =+"Total cost flight engineer (yearly)"&" "&+'1903 Aviation'!$C$16 -> Total cost flight engineer (yearly) EUR | C16: =+C15*C14 -> 76800 | E16: Starlink | G16: 30000 | H16: =IF(F16<>"", F16, IF(G16<>"", G16*$C$18, "")) -> 25500 | I16: =SUM(H16)/12 -> 2125 | K16: Internet 2000-10000 usd / månad
E17: Technical manuals | G17: 29500 | H17: =IF(F17<>"", F17, IF(G17<>"", G17*$C$18, "")) -> 25075 | I17: =SUM(H17)/12 -> 2089.5833 | K17: Manualer från tillverkaren
B18: =+'1903 Aviation'!B19 -> USD / EUR | C18: =+'1903 Aviation'!C19 -> 0.85 | E18: Electronic flight Bags (EFB) | G18: 40000 | H18: =IF(F18<>"", F18, IF(G18<>"", G18*$C$18, "")) -> 34000 | I18: =SUM(H18/12) -> 2833.3333 | K18: Jepessen, Satcom direct och ipads, APG, forflight,
E19: Flight data monitor | F19: 4000 | H19: =IF(F19<>"", F19, IF(G19<>"", G19*$C$18, "")) -> 4000 | I19: =SUM(H19/12) -> 333.33333 | K19: Uppföljningsprogram för aktuella flygningar
E20: Base (hangar m.m.) | F20: 130000 | H20: =IF(F20<>"", F20, IF(G20<>"", G20*$C$18, "")) -> 130000 | I20: =SUM(H20/12) -> 10833.333 | K20: Delad hangar
E21: Education | F21: 215000 | H21: =IF(F21<>"", F21, IF(G21<>"", G21*$C$18, "")) -> 215000 | I21: =H21/12 -> 17916.667 | K21: Simulatorutbildning för 4 piloter
E22: Tools technician | F22: 5000 | H22: =IF(F22<>"", F22, IF(G22<>"", G22*$C$18, "")) -> 5000 | I22: =H22/12 -> 416.66667 | K22: Löpande uppdatering av verktyg till hangaren
E23: Others (mobile, uniform, medical etc) | F23: 25000 | H23: =IF(F23<>"", F23, IF(G23<>"", G23*$C$18, "")) -> 25000 | I23: =SUM(H23)/12 -> 2083.3333 | K23: Mobil abonemang, uniform till piloter, kabin, tekniker
E24: Avinode | F24: 9000 | H24: =IF(F24<>"", F24, IF(G24<>"", G24*$C$18, "")) -> 9000 | I24: =SUM(H24)/12 -> 750
E25: Medair | G25: 22900 | H25: =IF(F25<>"", F25, IF(G25<>"", G25*$C$18, "")) -> 19465 | I25: =SUM(H25)/12 -> 1622.0833
E26: Total: | H26: =SUM(H5:H25) -> 2277076 | I26: =SUM(I5:I25) -> 189756.33

Sheet Variable costs
B2: Variale costs
B4: =+'1903 Aviation'!B19 -> USD / EUR | C4: =+'1903 Aviation'!C19 -> 0.85 | E4: Variable costs | F4: Input Hour - Liter | G4: Input Hour - EUR | H4: Input Hour - Dollar | I4: Hours | K4: Comments:
B5: =+'1903 Aviation'!B20 -> Fuel Price - EUR | C5: =+'1903 Aviation'!C20 -> 1.25 | E5: Fuel | F5: 1600 | I5: =+F5*C5 -> 2000
E6: En Route Fee | H6: 500 | I6: =IF(G6<>"", G6, IF(H6<>"", H6*$C$4, "")) -> 425 | K6: Eurocontrol, kostnaden att flyga över ett land. Liten ökning
E7: APU Honeywell | G7: 205 | I7: =IF(G7<>"", G7, IF(H7<>"", H7*$C$4, ""))*0.5 -> 102.5 | K7: Räknar med APU tid 50% av totala tiden
E8: Airframe Maintenance Labour | G8: 1500 | I8: =IF(G8<>"", G8, IF(H8<>"", H8*$C$4, "")) -> 1500 | K8: Avsättningar för kommande service
E9: Total: | I9: =SUM(I5:I8) -> 4027.5
E10: NOTE: Hotel, per diem, catering, landing, handling and parking are not included and are additional outside Bromma.
